zipstream/__init__.py
zipstream/compat.py
zipstream_new_2-1.1.8.dist-info/LICENSE
zipstream_new_2-1.1.8.dist-info/METADATA
zipstream_new_2-1.1.8.dist-info/WHEEL
zipstream_new_2-1.1.8.dist-info/top_level.txt
zipstream_new_2-1.1.8.dist-info/RECORD
